rpg_dice/__init__.py
tests/__init__.py
tests/test_mixed_dice.py
tests/test_roll.py
rpg_dice-0.2.0.dist-info/LICENSE
rpg_dice-0.2.0.dist-info/METADATA
rpg_dice-0.2.0.dist-info/WHEEL
rpg_dice-0.2.0.dist-info/top_level.txt
rpg_dice-0.2.0.dist-info/RECORD
