Metadata-Version: 2.1
Name: rpg-dice
Version: 0.2.0
Summary: A simple dice roller
Home-page: https://github.com/pfertyk/rpg-dice
Author: Paweł Fertyk
Author-email: pfertyk@pfertyk.me
License: UNKNOWN
Platform: UNKNOWN
Classifier: Programming Language :: Python :: 3
Classifier: License :: CC0 1.0 Universal (CC0 1.0) Public Domain Dedication
Classifier: Operating System :: OS Independent
